CSV_combiner/Spreadsheet_converter.py
CSV_combiner/__init__.py
CSV_combiner/csv_combiner.py
CSV_combiner/csv_tools.py
CSV_combiner-0.1.0.dist-info/LICENSE
CSV_combiner-0.1.0.dist-info/METADATA
CSV_combiner-0.1.0.dist-info/WHEEL
CSV_combiner-0.1.0.dist-info/top_level.txt
CSV_combiner-0.1.0.dist-info/RECORD
