Metadata-Version: 2.1
Name: CSV-combiner
Version: 0.1.0
Summary: Tool to compine multiple csv files into one file
Home-page: https://github.com/mo0haned/CSV-combiner
Author: Mohaned AbdElMonsef, Mohammed Magdy
Author-email: mo0han3d@gmail.com
License: BSD 2-clause
Platform: UNKNOWN
Classifier: Development Status :: 1 - Planning
Classifier: Intended Audience :: Science/Research
Classifier: License :: OSI Approved :: BSD License
Classifier: Operating System :: POSIX :: Linux
Classifier: Programming Language :: Python :: 2
Classifier: Programming Language :: Python :: 2.7
Classifier: Programming Language :: Python :: 3
Classifier: Programming Language :: Python :: 3.4
Classifier: Programming Language :: Python :: 3.5
License-File: LICENSE
Requires-Dist: pandas
